[
  {
    "foodName": "Chicken Biryani",
    "chefName": "Chef Rahim",
    "chefId": "CH001",
    "foodImage": "https://i.ibb.co.com/4gZkhgmr/hq720.jpg",
    "price": 250,
    "rating": 4.5,
    "deliveryArea": "Dhaka",
    "estimatedDeliveryTime": "30-40 min",
    "ingredients": ["Chicken", "Rice", "Spices", "Onion", "Yogurt"],
    "chefExperience": "5 years"
  },
  {
    "foodName": "Beef Steak",
    "chefName": "Chef Karim",
    "chefId": "CH002",
    "foodImage": "https://i.ibb.co.com/jP6RR05K/Perfect-Grilled-Steak-with-Herb-Butter-iowagirleats-Featured-1200x2-1.jpg",
    "price": 500,
    "rating": 5,
    "deliveryArea": "Dhaka",
    "estimatedDeliveryTime": "45-60 min",
    "ingredients": ["Beef", "Garlic", "Butter", "Pepper", "Salt"],
    "chefExperience": "8 years"
  },
  {
    "foodName": "Grilled Salmon",
    "chefName": "Chef Shila",
    "chefId": "CH003",
    "foodImage": "https://i.ibb.co.com/KzsVYpVZ/7969212-grilled-salmon-and-vegetables-with-charred-lemon-vinaigrette-beauty-501b80ab61a640d3bfacfa5f.jpg",
    "price": 450,
    "rating": 4.8,
    "deliveryArea": "Chittagong",
    "estimatedDeliveryTime": "30-35 min",
    "ingredients": ["Salmon", "Lemon", "Garlic", "Olive Oil", "Herbs"],
    "chefExperience": "3 years"
  },
  {
    "foodName": "Veggie Pizza",
    "chefName": "Chef Nabila",
    "chefId": "CH004",
    "foodImage": "https://i.ibb.co.com/n8RS8cZq/images-3.jpg",
    "price": 300,
    "rating": 4.2,
    "deliveryArea": "Sylhet",
    "estimatedDeliveryTime": "25-30 min",
    "ingredients": ["Flour", "Tomato", "Cheese", "Bell Pepper", "Onion"],
    "chefExperience": "3 years"
  },
  {
    "foodName": "Fried Chicken",
    "chefName": "Chef Sakil",
    "chefId": "CH005",
    "foodImage": "https://i.ibb.co.com/MYHsJTG/images-4.jpg",
    "price": 200,
    "rating": 4.6,
    "deliveryArea": "Dhaka",
    "estimatedDeliveryTime": "20-25 min",
    "ingredients": ["Chicken", "Flour", "Spices", "Oil"],
    "chefExperience": "3 years"
  },
  {
    "foodName": "Pasta Alfredo",
    "chefName": "Chef Jahan",
    "chefId": "CH006",
    "foodImage": "https://i.ibb.co.com/QFtbsNtf/images-5.jpg",
    "price": 350,
    "rating": 4.3,
    "deliveryArea": "Khulna",
    "estimatedDeliveryTime": "25-35 min",
    "ingredients": ["Pasta", "Cream", "Garlic", "Parmesan", "Butter"],
    "chefExperience": "3 years"
  },
  {
    "foodName": "Sushi Platter",
    "chefName": "Chef Rina",
    "chefId": "CH007",
    "foodImage": "https://i.ibb.co.com/nsTjc32D/images-6.jpg",
    "price": 600,
    "rating": 5,
    "deliveryArea": "Chittagong",
    "estimatedDeliveryTime": "50-60 min",
    "ingredients": ["Rice", "Fish", "Seaweed", "Soy Sauce", "Wasabi"],
    "chefExperience": "3 years"
  },
  {
    "foodName": "Beef Burger",
    "chefName": "Chef Tanvir",
    "chefId": "CH008",
    "foodImage": "https://i.ibb.co.com/PsR1CcGG/crispy-comte-cheesburgers-FT-RECIPE0921-6166c6552b7148e8a8561f7765ddf20b.jpg",
    "price": 180,
    "rating": 4.1,
    "deliveryArea": "Dhaka",
    "estimatedDeliveryTime": "15-20 min",
    "ingredients": ["Beef Patty", "Bun", "Cheese", "Lettuce", "Tomato"],
    "chefExperience": "3 years"
  }
]